{
	"sandbox_id": "ipdbrbgeuuozvuxrz5w6n",
	"feature": {
		"issue_number": 1367,
		"title": "Dashboard Page & Grid Layout"
	},
	"status": "running",
	"phase": "executing",
	"last_heartbeat": "2026-01-13T21:59:30.245937Z",
	"last_tool": "Bash",
	"session_id": "ipdbrbgeuuozvuxrz5w6n",
	"recent_output": [
		"💻 Bash: cat > .initiative-progress.jso...",
		"📖 Read: load-user-workspace.ts",
		"📖 Read: page.tsx",
		"📖 Read: loading.tsx",
		"📖 Read: paths.config.ts",
		"🔍 Grep: database.types.ts",
		"🔍 Grep: database.types.ts",
		"🔍 Grep: database.types.ts",
		"🔍 Grep: database.types.ts",
		"💻 Bash: mkdir -p apps/web/app/home/\\(u..."
	]
}