{
	"data": {
		"library": "/e2b-dev/e2b",
		"version": "latest",
		"topic": "template startup",
		"tokens": 1735,
		"content": "### Initialize New Sandbox Template with SDK\n\nSource: https://github.com/e2b-dev/e2b/blob/main/apps/web/src/app/(docs)/docs/sdk-reference/cli/v2.2.4/template/page.mdx\n\nInitializes a new sandbox template using the E2B SDK. Allows specifying the path, template name, and target language (typescript, python-sync, python-async).\n\n```bash\ne2b template init-v2 [options]\n```\n\n--------------------------------\n\n### Initialize E2B Sandbox Template with E2B CLI\n\nSource: https://github.com/e2b-dev/e2b/blob/main/apps/web/src/app/(docs)/docs/sdk-reference/cli/v1.0.0/template/page.mdx\n\nInitializes a new E2B sandbox template by creating a basic e2b.Dockerfile in the root directory. This command helps set up the basic structure for a new template.\n\n```bash\ne2b template init [options]\n```\n\n--------------------------------\n\n### Initialize Sandbox Template with E2B CLI\n\nSource: https://github.com/e2b-dev/e2b/blob/main/apps/web/src/app/(docs)/docs/sdk-reference/cli/v1.5.1/template/page.mdx\n\nCreates a basic E2B Dockerfile (./e2b.Dockerfile) in the root directory. This serves as a starting point for creating a new sandbox template, which can then be built using the `e2b template build` command.\n\n```bash\ne2b template init [options]\n\nOptions:\n - `-p, --path <path>`: change root directory where command is executed to <path> directory \n```\n\n--------------------------------\n\n### Build Sandbox Template with E2B CLI\n\nSource: https://github.com/e2b-dev/e2b/blob/main/apps/web/src/app/(docs)/docs/sdk-reference/cli/v1.5.1/template/page.mdx\n\nBuilds a sandbox template from a Dockerfile. It supports specifying the Dockerfile path, template name, start command, and various build-time configurations. This command creates an e2b.toml configuration file alongside the template.\n\n```bash\ne2b template build [options] [template]\n\nOptions:\n - `-p, --path <path>`: change root directory where command is executed to <path> directory \n - `-d, --dockerfile <file>`: specify path to Dockerfile. By default E2B tries to find e2b.Dockerfile or Dockerfile in root directory. \n - `-n, --name <template-name>`: specify sandbox template name. You can use the template name to start the sandbox with SDK. The template name must be lowercase and contain only letters, numbers, dashes and underscores. \n - `-c, --cmd <start-command>`: specify command that will be executed when the sandbox is started. \n - `--ready-cmd <ready-command>`: specify command that will need to exit 0 for the template to be ready. \n - `-t, --team <team-id>`: specify the team ID that the operation will be associated with. You can find team ID in the team settings in the E2B dashboard (https://e2b.dev/dashboard?tab=team). \n - `--config <e2b-toml>`: specify path to the E2B config toml. By default E2B tries to find ./e2b.toml in root directory. \n - `--cpu-count <cpu-count>`: specify the number of CPUs that will be used to run the sandbox. The default value is 2. \n - `--memory-mb <memory-mb>`: specify the amount of memory in megabytes that will be used to run the sandbox. Must be an even number. The default value is 512. \n - `--build-arg <args...>`: specify additional build arguments for the build command. The format should be <varname>=<value>. \n - `--no-cache`: skip cache when building the template. \n```\n\n--------------------------------\n\n### Initialize Sandbox Template with E2B CLI\n\nSource: https://github.com/e2b-dev/e2b/blob/main/apps/web/src/app/(docs)/docs/sdk-reference/cli/v2.0.1/template/page.mdx\n\nCreates a basic E2B Dockerfile (./e2b.Dockerfile) in the root directory. This serves as a starting point for defining a new sandbox template, which can then be built using the `e2b template build` command.\n\n```bash\ne2b template init [options]\n\nOptions:\n - `-p, --path <path>: change root directory where command is executed to <path> directory\n```\n\n--------------------------------\n\n### Publish Sandbox Template with E2B CLI\n\nSource: https://github.com/e2b-dev/e2b/blob/main/apps/web/src/app/(docs)/docs/sdk-reference/cli/v1.7.0/template/page.mdx\n\nPublishes a sandbox template, making it available for use. Options include specifying the path, configuration file, team ID, and flags to select templates interactively or skip confirmation.\n\n```bash\ne2b template publish [options] [template]\n\nOptions:\n - -p, --path <path>: change root directory where command is executed to <path> directory \n - --config <e2b-toml>: specify path to the E2B config toml. By default E2B tries to find ./e2b.toml in root directory. \n - -s, --select: select sandbox template from interactive list \n - -t, --team <team-id>: specify the team ID that the operation will be associated with. You can find team ID in the E2B dashboard (https://e2b.dev/dashboard?tab=team). \n - -y, --yes: skip manual publish confirmation\n```\n\n--------------------------------\n\n### Start Custom Sandbox with Template ID (JavaScript)\n\nSource: https://github.com/e2b-dev/e2b/blob/main/apps/web/src/app/(docs)/docs/quickstart/install-custom-packages/page.mdx\n\nStarts a new sandbox instance using a previously built custom template. The template ID is passed to the `Sandbox.create` method in JavaScript.\n\n```javascript\nimport { Sandbox } from '@e2b/code-interpreter'\n\nconst sbx = Sandbox.create({\n  template: 'YOUR_TEMPLATE_ID',\n})\n```\n\n--------------------------------\n\n### Build Sandbox Template with E2B CLI\n\nSource: https://github.com/e2b-dev/e2b/blob/main/apps/web/src/app/(docs)/docs/sdk-reference/cli/v1.0.1/template/page.mdx\n\nBuilds a sandbox template from a Dockerfile. It supports specifying the Dockerfile path, template name, start command, team ID, and build arguments. It also allows configuration of CPU and memory for the sandbox.\n\n```bash\ne2b template build [options] [template]\n\nOptions:\n  -p, --path <path>: change root directory where command is executed to <path> directory\n  -d, --dockerfile <file>: specify path to Dockerfile. By default E2B tries to find e2b.Dockerfile or Dockerfile in root directory.\n  -n, --name <template-name>: specify sandbox template name. You can use the template name to start the sandbox with SDK. The template name must be lowercase and contain only letters, numbers, dashes and underscores.\n  -c, --cmd <start-command>: specify command that will be executed when the sandbox is started.\n  -t, --team <team-id>: specify the team ID that the operation will be associated with. You can find team ID in the team settings in the E2B dashboard (https://e2b.dev/dashboard?tab=team).\n  --config <e2b-toml>: specify path to the E2B config toml. By default E2B tries to find ./e2b.toml in root directory.\n  --cpu-count <cpu-count>: specify the number of CPUs that will be used to run the sandbox. The default value is 2.\n  --memory-mb <memory-mb>: specify the amount of memory in megabytes that will be used to run the sandbox. Must be an even number. The default value is 512.\n  --build-arg <args...>: specify additional build arguments for the build command. The format should be <varname>=<value>.\n```\n\n--------------------------------\n\n### Publish Sandbox Template with E2B CLI\n\nSource: https://github.com/e2b-dev/e2b/blob/main/apps/web/src/app/(docs)/docs/sdk-reference/cli/v1.8.0/template/page.mdx\n\nPublishes a sandbox template, making it available for use by others. Options include specifying the path, config file, team ID, and interactively selecting a template or skipping confirmation.\n\n```bash\ne2b template publish [options] [template]\n\nOptions:\n  -p, --path <path>: change root directory where command is executed to <path> directory\n  --config <e2b-toml>: specify path to the E2B config toml. By default E2B tries to find ./e2b.toml in root directory.\n  -s, --select: select sandbox template from interactive list\n  -t, --team <team-id>: specify the team ID that the operation will be associated with. You can find team ID in the team settings in the E2B dashboard (https://e2b.dev/dashboard?tab=team).\n  -y, --yes: skip manual publish confirmation\n```\n\n--------------------------------\n\n### Start Custom Sandbox with Template ID (Python)\n\nSource: https://github.com/e2b-dev/e2b/blob/main/apps/web/src/app/(docs)/docs/quickstart/install-custom-packages/page.mdx\n\nStarts a new sandbox instance using a previously built custom template. The template ID is passed to the `Sandbox.create` method in Python.\n\n```python\nfrom e2b_code_interpreter import Sandbox\n\nsbx = Sandbox.create(template='YOUR_TEMPLATE_ID')\n```\n\n--------------------------------\n\n### Build Sandbox Template (e2b CLI)\n\nSource: https://github.com/e2b-dev/e2b/blob/main/apps/web/src/app/(docs)/docs/sdk-reference/cli/v2.2.0/template/page.mdx\n\nBuilds a sandbox template defined by a Dockerfile. It can specify the Dockerfile path, template name, start command, and resource allocation. Optionally, it can use build arguments and skip caching.\n\n```bash\ne2b template build [options] [template]\n\n# Example with options:\ne2b template build -n my-template -c \"npm start\" --cpu-count 4 --memory-mb 1024\n```\n\n--------------------------------\n\n### List Sandbox Templates (CLI)\n\nSource: https://github.com/e2b-dev/e2b/blob/main/apps/web/src/app/(docs)/docs/sdk-reference/cli/v1.5.2/template/page.mdx\n\nLists all available sandbox templates. It can filter templates by team ID.\n\n```bash\ne2b template list [options]\n\nOptions:\n - `-t, --team <team-id>: specify the team ID that the operation will be associated with. You can find team ID in the team settings in the E2B dashboard (https://e2b.dev/dashboard?tab=team). \n```\n\n--------------------------------\n\n### Initialize Sandbox Template (CLI)\n\nSource: https://github.com/e2b-dev/e2b/blob/main/apps/web/src/app/(docs)/docs/sdk-reference/cli/v1.5.2/template/page.mdx\n\nCreates a basic E2B Dockerfile in the root directory to help users start building a sandbox template. It supports specifying the target directory.\n\n```bash\ne2b template init [options]\n\nOptions:\n - `-p, --path <path>: change root directory where command is executed to <path> directory \n```\n\n--------------------------------\n\n### Publish E2B Sandbox Template with E2B CLI\n\nSource: https://github.com/e2b-dev/e2b/blob/main/apps/web/src/app/(docs)/docs/sdk-reference/cli/v2.2.1/template/page.mdx\n\nPublishes a sandbox template. Options include specifying the path, config file, selecting a template interactively, specifying the team ID, and skipping manual confirmation.\n\n```bash\ne2b template publish [options] [template]\n\nOptions:\n  -p, --path <path>: change root directory where command is executed to <path> directory\n  --config <e2b-toml>: specify path to the E2B config toml. By default E2B tries to find ./e2b.toml in root directory.\n  -s, --select: select sandbox template from interactive list\n  -t, --team <team-id>: specify the team ID that the operation will be associated with.\n  -y, --yes: skip manual publish confirmation\n```\n\n--------------------------------\n\n### Build Sandbox Template - E2B CLI\n\nSource: https://github.com/e2b-dev/e2b/blob/main/apps/web/src/app/(docs)/docs/sdk-reference/cli/v1.4.3/template/page.mdx\n\nBuilds a sandbox template using a Dockerfile. It can specify the Dockerfile path, template name, start command, team association, CPU/memory limits, and build arguments. It also supports skipping the cache.\n\n```bash\ne2b template build [options] [template]\n\nOptions:\n - `-p, --path <path>: change root directory where command is executed to <path> directory \n - `-d, --dockerfile <file>: specify path to Dockerfile. By default E2B tries to find e2b.Dockerfile or Dockerfile in root directory. \n - `-n, --name <template-name>: specify sandbox template name. You can use the template name to start the sandbox with SDK. The template name must be lowercase and contain only letters, numbers, dashes and underscores. \n - `-c, --cmd <start-command>: specify command that will be executed when the sandbox is started. \n - `-t, --team <team-id>: specify the team ID that the operation will be associated with. You can find team ID in the team settings in the E2B dashboard (https://e2b.dev/dashboard?tab=team). \n - `--config <e2b-toml>: specify path to the E2B config toml. By default E2B tries to find ./e2b.toml in root directory. \n - `--cpu-count <cpu-count>: specify the number of CPUs that will be used to run the sandbox. The default value is 2. \n - `--memory-mb <memory-mb>: specify the amount of memory in megabytes that will be used to run the sandbox. Must be an even number. The default value is 512. \n - `--build-arg <args...>: specify additional build arguments for the build command. The format should be <varname>=<value>. \n - `--no-cache: skip cache when building the template. \n```\n\n--------------------------------\n\n### Start Custom Sandbox - JavaScript and Python\n\nSource: https://github.com/e2b-dev/e2b/blob/main/apps/web/src/app/(docs)/docs/sandbox-template/page.mdx\n\nCreates and runs a custom sandbox using a template ID. The code examples demonstrate how to import the Sandbox class, create a sandbox instance with a specific template, and execute code within it, leveraging installed dependencies like 'cowsay'.\n\n```js\nimport { Sandbox } from '@e2b/code-interpreter'\n\n// Your template ID from the previous step\nconst templateID = 'id-of-your-template' // $HighlightLine\n// Pass the template ID to the `Sandbox.create` method\nconst sandbox = await Sandbox.create(templateID) // $HighlightLine\n\n// The template installed cowsay, so we can use it\nconst execution = await sandbox.runCode(`\nimport cowsay\ncowsay.say('Hello from E2B!')\n`)\n\nconsole.log(execution.stdout)\n```\n\n```python\nfrom e2b_code_interpreter import Sandbox\n\n# Your template ID from the previous step\ntemplate_id = 'id-of-your-template' # $HighlightLine\n# Pass the template ID to the `Sandbox.create` method\nsandbox = Sandbox.create(template_id) # $HighlightLine\n\n# The template installed cowsay, so we can use it\nexecution = sandbox.run_code(\"\"\"\nimport cowsay\ncowsay.say('Hello from E2B!')\n\"\"\")\n\nprint(execution.stdout)\n```",
		"chunks": null,
		"metadata": {}
	},
	"cached_at": 1764175607.9275184,
	"params": {
		"owner": "e2b-dev",
		"repo": "e2b",
		"version": "latest",
		"topic": "template startup",
		"tokens": 3000,
		"format": "txt"
	}
}
